README.md
setup.py
django_request_context/__init__.py
django_request_context/__version__.py
django_request_context/exceptions.py
django_request_context/globals.py
django_request_context/middleware.py
django_request_context/request_context.py
django_request_context.egg-info/PKG-INFO
django_request_context.egg-info/SOURCES.txt
django_request_context.egg-info/dependency_links.txt
django_request_context.egg-info/requires.txt
django_request_context.egg-info/top_level.txt