Metadata-Version: 2.1
Name: django-request-context
Version: 0.1.0
Summary: Django middleware which provide request and g objectall of which are accessible everywhere, and thread isolation, just like used in flask.
Home-page: https://github.com/schecterdamien/django-request-context
Author: wujinjing
Author-email: schecterfirst@gmail.com
License: MIT
Keywords: django request-context global-request
Platform: UNKNOWN
Classifier: License :: OSI Approved :: MIT License
Classifier: Programming Language :: Python
Classifier: Programming Language :: Python :: 3
Classifier: Programming Language :: Python :: 3.6
Classifier: Programming Language :: Python :: Implementation :: CPython
Classifier: Programming Language :: Python :: Implementation :: PyPy
Requires-Python: >=3.4.1
